odoo/addons/ssi_landed_cost/README.rst
odoo/addons/ssi_landed_cost/__init__.py
odoo/addons/ssi_landed_cost/__manifest__.py
odoo/addons/ssi_landed_cost/models/__init__.py
odoo/addons/ssi_landed_cost/models/landed_cost_type.py
odoo/addons/ssi_landed_cost/models/landed_cost_type_cost.py
odoo/addons/ssi_landed_cost/models/stock_landed_cost.py
odoo/addons/ssi_landed_cost/security/ir.model.access.csv
odoo/addons/ssi_landed_cost/security/res_group_data.xml
odoo/addons/ssi_landed_cost/static/description/icon.png
odoo/addons/ssi_landed_cost/views/landed_cost_type_views.xml
odoo/addons/ssi_landed_cost/views/stock_landed_cost_views.xml
odoo14_addon_ssi_landed_cost-14.0.2.0.0.dist-info/METADATA
odoo14_addon_ssi_landed_cost-14.0.2.0.0.dist-info/WHEEL
odoo14_addon_ssi_landed_cost-14.0.2.0.0.dist-info/top_level.txt
odoo14_addon_ssi_landed_cost-14.0.2.0.0.dist-info/RECORD
